metadocs/__init__.py
metadocs/commands.py
metadocs/conf.py
metadocs/utils.py
metadocs/include/.DS_Store
metadocs/include/How_To_Use_Metadocs.md
metadocs/include/Writing_Sphinx_Documentation.md
metadocs/include/index.md
metadocs/include/material-icons.woff2
metadocs/include/material-style.css
metadocs/include/mkdocs.yml
metadocs/include/example_project/.DS_Store
metadocs/include/example_project/Makefile
metadocs/include/example_project/__init__.py
metadocs/include/example_project/make.bat
metadocs/include/example_project/classif/__init__.py
metadocs/include/example_project/classif/inference.py
metadocs/include/example_project/classif/models.py
metadocs/include/example_project/classif/__pycache__/__init__.cpython-36.pyc
metadocs/include/example_project/classif/__pycache__/ds.cpython-36.pyc
metadocs/include/example_project/classif/__pycache__/models.cpython-36.pyc
metadocs/include/example_project/datasets/__init__.py
metadocs/include/example_project/datasets/datasets.py
metadocs/include/example_project/datasets/__pycache__/__init__.cpython-36.pyc
metadocs/include/example_project/datasets/__pycache__/datasets.cpython-36.pyc
metadocs/include/example_project/matching/__init__.py
metadocs/include/example_project/matching/elastic.py
metadocs/include/example_project/matching/search.py
metadocs/include/example_project/matching/__pycache__/__init__.cpython-36.pyc
metadocs/include/example_project/matching/__pycache__/elastic.cpython-36.pyc
metadocs/include/example_project/matching/__pycache__/haha.cpython-36.pyc
metadocs/include/example_project/matching/__pycache__/module.cpython-36.pyc
metadocs/include/example_project/matching/__pycache__/search.cpython-36.pyc
metadocs/include/example_project/source/.DS_Store
metadocs/include/example_project/source/conf.py
metadocs/include/example_project/source/example_project.classif.inference.rst
metadocs/include/example_project/source/example_project.classif.models.rst
metadocs-0.4.0.1.dist-info/METADATA
metadocs-0.4.0.1.dist-info/RECORD
metadocs-0.4.0.1.dist-info/WHEEL
metadocs-0.4.0.1.dist-info/top_level.txt
