Metadata-Version: 2.1
Name: metadocs
Version: 0.4.0.1
Summary: The docs of your docs: manage sphinx documentations with mkdocs
Home-page: https://github.com/entrepreneur-interet-general/metadocs
Author: Victor Schmidt
Author-email: vsch@protonmail.com
License: AGPL
Keywords: documentation doc sphinx mkdocs metadocs
Platform: UNKNOWN
Requires-Dist: watchdog
Requires-Dist: sphinx (>=1.7.6)
Requires-Dist: mkdocs
Requires-Dist: sphinx-rtd-theme (>=0.4.0)
Requires-Dist: mkdocs-material
Requires-Dist: pexpect
Requires-Dist: pygments
